kalash/__init__.py
kalash/collectors.py
kalash/config.py
kalash/filter.py
kalash/kalash_test_loader.py
kalash/last_result_filter.py
kalash/log.py
kalash/metaparser.py
kalash/run.py
kalash/smuggle.py
kalash/spec.py
kalash/spec.schema.json
kalash/spec.yaml
kalash/test_case.py
kalash/testutils.py
kalash/utils.py
kalash/built_docs/.DS_Store
kalash/built_docs/index.html
kalash/built_docs/kalash.html
kalash/built_docs/search.js
kalash/built_docs/html/.DS_Store
kalash/built_docs/html/kalash/collectors.html
kalash/built_docs/html/kalash/config.html
kalash/built_docs/html/kalash/filter.html
kalash/built_docs/html/kalash/index.html
kalash/built_docs/html/kalash/kalash_test_loader.html
kalash/built_docs/html/kalash/last_result_filter.html
kalash/built_docs/html/kalash/log.html
kalash/built_docs/html/kalash/metaparser.html
kalash/built_docs/html/kalash/run.html
kalash/built_docs/html/kalash/smuggle.html
kalash/built_docs/html/kalash/spec.html
kalash/built_docs/html/kalash/test_case.html
kalash/built_docs/html/kalash/testutils.html
kalash/built_docs/html/kalash/utils.html
kalash/built_docs/html/res/kalash.svg
kalash/built_docs/html/res/kalash2.png
kalash/built_docs/html/res/kalash2.svg
kalash/built_docs/html/res/kalash_flow.svg
kalash/built_docs/kalash/collectors.html
kalash/built_docs/kalash/config.html
kalash/built_docs/kalash/filter.html
kalash/built_docs/kalash/kalash_test_loader.html
kalash/built_docs/kalash/last_result_filter.html
kalash/built_docs/kalash/log.html
kalash/built_docs/kalash/metaparser.html
kalash/built_docs/kalash/run.html
kalash/built_docs/kalash/smuggle.html
kalash/built_docs/kalash/spec.html
kalash/built_docs/kalash/test_case.html
kalash/built_docs/kalash/testutils.html
kalash/built_docs/kalash/utils.html
kalash/pdoc/advanced_config.md
kalash/pdoc/automation_servers.md
kalash/pdoc/basic_usage.md
kalash/pdoc/contributing.md
kalash/pdoc/features.md
kalash/pdoc/header.md
kalash/pdoc/python_spec.md
kalash/pdoc/trailer.md
kalash/pdoc/yaml_spec.md
kalash-4.0.0.dist-info/LICENSE
kalash-4.0.0.dist-info/METADATA
kalash-4.0.0.dist-info/WHEEL
kalash-4.0.0.dist-info/entry_points.txt
kalash-4.0.0.dist-info/top_level.txt
kalash-4.0.0.dist-info/RECORD
