Metadata-Version: 2.1
Name: kalash
Version: 4.0.0
Summary: Test runner made for scalable automation based on standard `unittest` Python module
Home-page: https://github.com/Technica-Engineering/kalash
Author: Product Testing Technica Engineering GmbH
Author-email: krzysztof.czarnecki@technica-engineering.de
License: GPLv3
Keywords: automation,testing,systems,devices
Platform: UNKNOWN
Classifier: License :: OSI Approved :: GNU General Public License v3 (GPLv3)
Classifier: Programming Language :: Python :: 3
Classifier: Programming Language :: Python :: 3.7
Requires-Python: >=3.6
License-File: LICENSE
Requires-Dist: pyyaml
Requires-Dist: argparse
Requires-Dist: unittest-xml-reporting
Requires-Dist: parameterized
Requires-Dist: toolz
Requires-Dist: dataclasses-jsonschema
Provides-Extra: dev
Requires-Dist: pdoc3 ; extra == 'dev'
Requires-Dist: flake8 ; extra == 'dev'
Requires-Dist: twine ; extra == 'dev'
Requires-Dist: setuptools ; extra == 'dev'
Requires-Dist: autopep8 ; extra == 'dev'
